{"github_org": "blb-vertnet", "last_report_url": "https://api.github.com/repos/jotegui/statReports/contents/data/BLB-blb_2014_07.json", "downloads": {"downloads_period": 273, "records_unique": 661, "countries_list": ["Brazil", "Chile", "Israel", "Mexico", "United States"], "records": 763, "queries": [{"query": "buteo regalis", "records": 2, "times": 1}, {"query": "pomatorhinus ruficollis", "records": 1, "times": 1}, {"query": "tamiasciurus hudsonicus", "records": 1, "times": 1}, {"query": "grasshopper institutioncode:BLB", "records": 2, "times": 1}, {"query": "Corvus corax", "records": 2, "times": 1}, {"query": "Charadrius montanus", "records": 81, "times": 3}, {"query": "Anaxyrus americanus", "records": 2, "times": 1}, {"query": "urocitellus", "records": 1, "times": 1}, {"query": "Lontra canadensis", "records": 1, "times": 2}, {"query": "nayarit", "records": 1, "times": 1}, {"query": "Acris gryllus", "records": 1, "times": 1}, {"query": "Rhynchopsitta", "records": 2, "times": 1}, {"query": "Anaxyrus woodhousii", "records": 2, "times": 1}, {"query": "ochotona princeps", "records": 2, "times": 1}, {"query": "eptesicus", "records": 2, "times": 1}, {"query": "Acris crepitans", "records": 2, "times": 1}, {"query": "anas laysanensis", "records": 81, "times": 1}, {"query": "country:\"brazil\"", "records": 1, "times": 2}, {"query": "Toxostoma lecontei", "records": 2, "times": 1}, {"query": "country:\"Suriname\"", "records": 1, "times": 1}, {"query": "rana sylvatica", "records": 81, "times": 1}, {"query": "panthera onca", "records": 1, "times": 1}, {"query": "castor canadensis", "records": 81, "times": 1}, {"query": "urocitellus beldingi", "records": 81, "times": 1}, {"query": "Alouatta", "records": 2, "times": 1}, {"query": "myocastor coypus", "records": 1, "times": 1}, {"query": "alouatta seniculus", "records": 1, "times": 1}], "downloads": 31, "countries": [{"country": "Brazil", "times": 3}, {"country": "Chile", "times": 1}, {"country": "Israel", "times": 2}, {"country": "Mexico", "times": 5}, {"country": "United States", "times": 20}], "records_period": 1909881, "dates": [{"date": "2014-08-03", "times": 1}, {"date": "2014-08-05", "times": 9}, {"date": "2014-08-07", "times": 1}, {"date": "2014-08-13", "times": 2}, {"date": "2014-08-14", "times": 3}, {"date": "2014-08-16", "times": 1}, {"date": "2014-08-17", "times": 1}, {"date": "2014-08-18", "times": 1}, {"date": "2014-08-21", "times": 1}, {"date": "2014-08-24", "times": 1}, {"date": "2014-08-25", "times": 1}, {"date": "2014-08-26", "times": 1}, {"date": "2014-08-27", "times": 4}, {"date": "2014-08-28", "times": 2}, {"date": "2014-08-30", "times": 1}, {"date": "2014-08-31", "times": 1}]}, "github_repo": "blb", "inst": "BLB", "year": {"searches": 175, "records": 130017, "downloads": 104, "records_period": 450627, "s_records": 4862, "downloads_period": 61}, "report_month_string": "August, 2014", "searches": {"searches": 19, "dates": [{"date": "2014-08-01", "times": 2}, {"date": "2014-08-07", "times": 1}, {"date": "2014-08-14", "times": 2}, {"date": "2014-08-17", "times": 1}, {"date": "2014-08-20", "times": 1}, {"date": "2014-08-21", "times": 8}, {"date": "2014-08-23", "times": 1}, {"date": "2014-08-24", "times": 1}, {"date": "2014-08-25", "times": 1}, {"date": "2014-08-26", "times": 1}], "countries": [{"country": "Colombia", "times": 1}, {"country": "Guatemala", "times": 5}, {"country": "Portugal", "times": 1}, {"country": "United Kingdom", "times": 1}, {"country": "United States", "times": 9}, {"country": "Unknown", "times": 2}], "records": 486, "countries_list": ["Colombia", "Guatemala", "Portugal", "United Kingdom", "United States", "Unknown"], "queries": [{"query": "omophron", "records": 1, "times": 1}, {"query": "institutioncode:BLB", "records": 100, "times": 1}, {"query": "tapir", "records": 4, "times": 1}, {"query": "puget sound white-crowned sparrow", "records": 99, "times": 2}, {"query": "Panthera onca", "records": 1, "times": 1}, {"query": "grasshopper institutioncode:BLB", "records": 100, "times": 1}, {"query": "Trogon violaceus", "records": 3, "times": 1}, {"query": "Tapirus bairdii", "records": 3, "times": 4}, {"query": "Giraffe", "records": 1, "times": 3}, {"query": "rosefinch", "records": 1, "times": 1}, {"query": "matinicus rock", "records": 43, "times": 1}, {"query": "green-backed tit", "records": 18, "times": 1}, {"query": "chip sparrow", "records": 1, "times": 1}]}, "report_month": "2014/08", "url": "http://hymfiles.biosci.ohio-state.edu:8080/ipt/resource.do?r=blb", "created_at": "2014/09/02", "col": "blb", "history": {"searches": 175, "downloads_period": 61, "downloads": 104, "records_period": 450627, "s_records": 4862, "records": 130017}}