{"github_org": "csuc-vertnet", "last_report_url": "", "downloads": {"downloads_period": 326, "records_unique": 1, "countries_list": ["United States"], "records": 1, "queries": [{"query": "specificepithet:auratus genus:Mesocricetus", "records": 1, "times": 1}], "downloads": 1, "countries": [{"country": "United States", "times": 1}], "records_period": 4108714, "dates": [{"date": "2015-02-27", "times": 1}]}, "github_repo": "csuc-mammals", "inst": "CSUC", "year": {"searches": 4, "downloads_period": 0, "downloads": 1, "records_period": 0, "s_records": 301, "records": 1}, "report_month_string": "February, 2015", "searches": {"searches": 4, "dates": [{"date": "2015-02-26", "times": 3}, {"date": "2015-02-27", "times": 1}], "countries": [{"country": "United States", "times": 4}], "records": 301, "countries_list": ["United States"], "queries": [{"query": "specificepithet:cricetus genus:cricetus", "records": 1, "times": 1}, {"query": "institutioncode:csuc", "records": 100, "times": 3}]}, "report_month": "2015/02", "url": "http://ipt.vertnet.org:8080/ipt/resource.do?r=csuc_mammals", "created_at": "2015/03/08", "col": "csuc_mammals", "history": {"searches": 4, "downloads_period": 0, "downloads": 1, "records_period": 0, "s_records": 301, "records": 1}}