{"github_org": "flmnh-vertnet", "last_report_url": "https://api.github.com/repos/jotegui/statReports/contents/data/FLMNH-herpetology_2014_09.json", "downloads": {"downloads_period": 166, "records_unique": 2862, "countries_list": ["Brazil", "Mexico", "Paraguay", "Philippines", "United States", "Unknown"], "records": 2934, "queries": [{"query": "Chiropterotriton chiropterus", "records": 648, "times": 1}, {"query": "specificepithet:montezumae", "records": 648, "times": 1}, {"query": "macrochelys temminckii", "records": 750, "times": 1}, {"query": "genus:desmognathus institutioncode:flmnh year >= 1959 year <= 1961", "records": 750, "times": 1}, {"query": "MINDORO", "records": 750, "times": 1}, {"query": "clemmys guttata", "records": 20, "times": 1}, {"query": "alligator mississippiensis", "records": 750, "times": 1}, {"query": "Bothrops jararaca", "records": 648, "times": 1}, {"query": "ambystoma opacum", "records": 20, "times": 1}, {"query": "Leptopelis calcaratus", "records": 648, "times": 1}, {"query": "batrachoseps wrighti", "records": 100, "times": 1}, {"query": "Paraguay", "records": 11, "times": 1}, {"query": "notophthalmus meridionalis", "records": 11, "times": 4}, {"query": "agalychnis dacnicolor", "records": 20, "times": 1}, {"query": "malacochersus tornieri", "records": 20, "times": 1}, {"query": "glyptemys insculpta", "records": 750, "times": 2}, {"query": "aneides lugubris", "records": 750, "times": 1}, {"query": "stateprovince:\"Texas\" class:Amphibia year >= 1888 year <= 2014", "records": 20, "times": 1}], "downloads": 22, "countries": [{"country": "Brazil", "times": 1}, {"country": "Mexico", "times": 2}, {"country": "Paraguay", "times": 1}, {"country": "Philippines", "times": 1}, {"country": "United States", "times": 16}, {"country": "Unknown", "times": 1}], "records_period": 1059512, "dates": [{"date": "2014-10-13", "times": 2}, {"date": "2014-10-17", "times": 1}, {"date": "2014-10-20", "times": 1}, {"date": "2014-10-21", "times": 1}, {"date": "2014-10-23", "times": 4}, {"date": "2014-10-24", "times": 1}, {"date": "2014-10-25", "times": 2}, {"date": "2014-10-27", "times": 5}, {"date": "2014-10-28", "times": 2}, {"date": "2014-10-29", "times": 2}, {"date": "2014-10-31", "times": 1}]}, "github_repo": "herpetology", "inst": "FLMNH", "year": {"searches": 1838, "records": 235974, "downloads": 314, "records_period": 5797717, "s_records": 37545, "downloads_period": 389}, "report_month_string": "October, 2014", "searches": {"searches": 141, "dates": [{"date": "2014-10-10", "times": 1}, {"date": "2014-10-11", "times": 4}, {"date": "2014-10-12", "times": 2}, {"date": "2014-10-13", "times": 3}, {"date": "2014-10-14", "times": 1}, {"date": "2014-10-15", "times": 6}, {"date": "2014-10-17", "times": 7}, {"date": "2014-10-18", "times": 17}, {"date": "2014-10-19", "times": 5}, {"date": "2014-10-20", "times": 1}, {"date": "2014-10-22", "times": 22}, {"date": "2014-10-23", "times": 10}, {"date": "2014-10-24", "times": 5}, {"date": "2014-10-26", "times": 1}, {"date": "2014-10-27", "times": 2}, {"date": "2014-10-28", "times": 4}, {"date": "2014-10-29", "times": 10}, {"date": "2014-10-30", "times": 30}, {"date": "2014-10-31", "times": 10}], "countries": [{"country": "Argentina", "times": 2}, {"country": "Colombia", "times": 1}, {"country": "Germany", "times": 2}, {"country": "Ireland", "times": 1}, {"country": "Israel", "times": 2}, {"country": "Mexico", "times": 21}, {"country": "United Kingdom", "times": 13}, {"country": "United States", "times": 99}], "records": 1351, "countries_list": ["Argentina", "Colombia", "Germany", "Ireland", "Israel", "Mexico", "United Kingdom", "United States"], "queries": [{"query": "Conopsis biserialis", "records": 7, "times": 8}, {"query": "Riopa sundevallii", "records": 27, "times": 1}, {"query": "Crocodylus niloticus", "records": 4, "times": 14}, {"query": "Aspidoscelis sexlineata (Alabama)", "records": 14, "times": 1}, {"query": "kinixys erosa", "records": 3, "times": 1}, {"query": "Chiasmocleis albopunctata", "records": 12, "times": 1}, {"query": "stateprovince:\"Los Santos\" country:\"Panama\" class:Reptilia", "records": 3, "times": 2}, {"query": "notophthalmus meridionalis", "records": 3, "times": 1}, {"query": "county:\"Hamilton\" stateprovince:\"texas\"", "records": 6, "times": 4}, {"query": "Stigmochelys pardalis", "records": 52, "times": 1}, {"query": "Kinosternon acutum", "records": 5, "times": 1}, {"query": "Epicrates maurus", "records": 16, "times": 1}, {"query": "lampropeltis calligaster travis texas", "records": 4, "times": 1}, {"query": "Ceratophrys calcarata", "records": 1, "times": 1}, {"query": "Eleutherodactylus counouspeus", "records": 2, "times": 3}, {"query": "STENORRHINA DEGENHARDTII", "records": 12, "times": 2}, {"query": "country:\"Panama\" specificepithet:leptophrys genus:Ameiva", "records": 9, "times": 1}, {"query": "Corallus annulatus", "records": 4, "times": 1}, {"query": "Ameiva polops", "records": 1, "times": 2}, {"query": "Aspidoscelis sexlineata alabama", "records": 14, "times": 1}, {"query": "corallus caninus", "records": 12, "times": 1}, {"query": "leptopelis calcaratus", "records": 2, "times": 2}, {"query": "Staurotypus triporcatus", "records": 15, "times": 6}, {"query": "Elgaria panamintina", "records": 1, "times": 34}, {"query": "Rana forreri", "records": 2, "times": 1}, {"query": "Chrysemys alabama", "records": 3, "times": 1}, {"query": "crocodylus moreletii", "records": 2, "times": 1}, {"query": "Eublepharis macularius", "records": 38, "times": 4}, {"query": "alligator sinensis", "records": 8, "times": 7}, {"query": "stateprovince:\"Los Santos\" country:\"Panama\" class:Amphibia", "records": 5, "times": 1}, {"query": "Leptopelis calcaratus", "records": 2, "times": 5}, {"query": "bothriechis marchi", "records": 7, "times": 1}, {"query": "Dermatemys mawii", "records": 31, "times": 3}, {"query": "Lithobates forreri", "records": 8, "times": 1}, {"query": "Pseudotriton ruber stateprovince:\"New York\"", "records": 4, "times": 2}, {"query": "Conopsis lineata", "records": 1, "times": 4}, {"query": "Eleutherodactylus auriculatus", "records": 4, "times": 1}, {"query": "genus:desmognathus institutioncode:flmnh year >= 1959 year <= 1961", "records": 100, "times": 1}, {"query": "Claudius angustatus", "records": 10, "times": 1}, {"query": "Kinosternon scorpioides", "records": 37, "times": 2}, {"query": "TESTUDO GRAECA ISRAEL", "records": 9, "times": 2}, {"query": "Opheodrys aestivus Alabama", "records": 9, "times": 2}, {"query": "dermatemys mawii", "records": 31, "times": 5}, {"query": "thamnophis melanogaster", "records": 18, "times": 1}, {"query": "Ambystoma maculatum Alabama", "records": 6, "times": 1}, {"query": "genus:Desmognathus recordedby:Martof year >= 1960 year <= 1961", "records": 5, "times": 2}, {"query": "Furcifer bifidus", "records": 1, "times": 1}]}, "report_month": "2014/10", "url": "http://ipt.flmnh.ufl.edu:8080/ipt/resource.do?r=herpetology", "created_at": "2014/11/02", "col": "herpetology", "history": {"searches": 1838, "records": 257428, "downloads": 397, "records_period": 11834580, "s_records": 37545, "downloads_period": 754}}