{"github_org": "rom-vertnet", "last_report_url": "https://api.github.com/repos/jotegui/statReports/contents/data/ROM-vposteology_2014_11.json", "downloads": {"downloads_period": 238, "records_unique": 161, "countries_list": ["Germany", "Mexico", "South Africa", "United States", "Unknown"], "records": 189, "queries": [{"query": "crotalus molossus", "records": 1, "times": 1}, {"query": "Geomys bursarius", "records": 1, "times": 1}, {"query": "panthera", "records": 1, "times": 1}, {"query": "mustela nivalis", "records": 1, "times": 1}, {"query": "Canis rufus type:specimen", "records": 1, "times": 1}, {"query": "Aneides", "records": 1, "times": 2}, {"query": "Lacertidae", "records": 1, "times": 1}, {"query": "peromyscus leucopus", "records": 1, "times": 1}, {"query": "crotalus lepidus", "records": 1, "times": 1}, {"query": "spermophilus beecheyi", "records": 1, "times": 1}, {"query": "megascops asio", "records": 1, "times": 1}, {"query": "puma concolor", "records": 1, "times": 1}, {"query": "testudinidae", "records": 1, "times": 1}, {"query": "trimorphodon biscutatus", "records": 1, "times": 1}, {"query": "Taricha", "records": 1, "times": 1}, {"query": "gambelia wislizenii", "records": 1, "times": 1}, {"query": "Baiomys taylori", "records": 1, "times": 1}, {"query": "\"spermophilus mexicanus\" stateprovince:\"texas\"", "records": 1, "times": 2}, {"query": "spea bombifrons", "records": 1, "times": 1}, {"query": "micrurus fulvius", "records": 1, "times": 1}, {"query": "crotalus willardi", "records": 1, "times": 1}, {"query": "Eleutherodactylus planirostris", "records": 1, "times": 1}, {"query": "lynx", "records": 1, "times": 2}, {"query": "Batrachoseps", "records": 1, "times": 1}], "downloads": 27, "countries": [{"country": "Germany", "times": 1}, {"country": "Mexico", "times": 1}, {"country": "South Africa", "times": 1}, {"country": "United States", "times": 22}, {"country": "Unknown", "times": 2}], "records_period": 1054698, "dates": [{"date": "2014-12-02", "times": 3}, {"date": "2014-12-03", "times": 3}, {"date": "2014-12-04", "times": 3}, {"date": "2014-12-05", "times": 4}, {"date": "2014-12-07", "times": 1}, {"date": "2014-12-08", "times": 1}, {"date": "2014-12-10", "times": 2}, {"date": "2014-12-12", "times": 4}, {"date": "2014-12-15", "times": 2}, {"date": "2014-12-17", "times": 1}, {"date": "2014-12-26", "times": 1}, {"date": "2014-12-28", "times": 1}, {"date": "2014-12-30", "times": 1}]}, "github_repo": "vertebratepalaeorecentskeletons", "inst": "ROM", "year": {"searches": 480, "dates": [{"date": "2014-03-29", "times": 1}, {"date": "2014-03-30", "times": 1}, {"date": "2014-03-31", "times": 9}], "countries": [{"country": "United Kingdom", "times": 1}, {"country": "United States", "times": 10}], "downloads": 361, "records_period": 835908, "s_records": 3984, "downloads_period": 81, "countries_list": ["United Kingdom", "United States"], "records": 5140, "queries": [{"query": "specificepithet:scrofa genus:sus", "times": 6, "records": 38}, {"query": "specificepithet:scrofa genus:Sus", "times": 1, "records": 38}, {"query": "sus scrofa", "times": 2, "records": 38}, {"query": "specificepithet:scrofa genus:sus institutioncode:utep OR CRCM OR hsu OR lacm OR ms OR mvz OR uam OR ummz OR nysm OR psm OR amnh OR cas OR uczm OR ucmp OR fmnh OR ku OR sbmnh OR cuml OR lsumz OR ubcbbm OR mcz OR rom OR tcwc OR nmnh OR dmns OR ccber OR isu OR flmnh", "times": 1, "records": 38}, {"query": "sus scrofa institutioncode:utep OR CRCM OR hsu OR lacm OR msb OR mvz OR uam OR ummz OR nysm OR psm OR amnh OR cas OR uczm OR ucmp OR fmnh OR ku OR sbmnh OR cuml OR lsumz OR ubcbbm OR mcz OR rom OR tcwc OR nmnh OR dmns OR ccber OR isu OR flmnh", "times": 1, "records": 38}]}, "report_month_string": "December, 2014", "searches": {"searches": 27, "dates": [{"date": "2014-12-03", "times": 6}, {"date": "2014-12-06", "times": 3}, {"date": "2014-12-07", "times": 2}, {"date": "2014-12-08", "times": 1}, {"date": "2014-12-09", "times": 2}, {"date": "2014-12-12", "times": 1}, {"date": "2014-12-17", "times": 2}, {"date": "2014-12-21", "times": 1}, {"date": "2014-12-26", "times": 9}], "countries": [{"country": "Australia", "times": 1}, {"country": "Brazil", "times": 1}, {"country": "Colombia", "times": 2}, {"country": "Mexico", "times": 1}, {"country": "United States", "times": 22}], "records": 200, "countries_list": ["Australia", "Brazil", "Colombia", "Mexico", "United States"], "queries": [{"query": "Tremarctos ornatus", "records": 1, "times": 2}, {"query": "choloepus didactylus", "records": 1, "times": 1}, {"query": "Rom Equus", "records": 45, "times": 1}, {"query": "Phascolarctos cinereus", "records": 1, "times": 1}, {"query": "Chaetophractus villosus", "records": 2, "times": 1}, {"query": "thylacinus cynocephalus", "records": 2, "times": 7}, {"query": "Eublepharis macularius", "records": 15, "times": 2}, {"query": "Echeneis neucratoides", "records": 1, "times": 1}, {"query": "Phrynosoma cornutum country:\"Mexico\"", "records": 1, "times": 1}, {"query": "ROM Equus type:specimen", "records": 45, "times": 2}, {"query": "\"Cryptotis parva\" stateprovince:\"Texas\"", "records": 1, "times": 1}, {"query": "thylacinus", "records": 2, "times": 2}, {"query": "Crotalus willardi stateprovince:\"Arizona\"", "records": 1, "times": 1}, {"query": "colossoma macropomum", "records": 3, "times": 1}, {"query": "Serinus canaria year >= 1990 year <= 2014", "records": 2, "times": 1}, {"query": "Ophisaurus year >= 1980 year <= 2014", "records": 1, "times": 2}]}, "report_month": "2014/12", "url": "http://gbif.rom.on.ca:8180/ipt/resource.do?r=vposteology", "created_at": "2015/01/02", "col": "vposteology", "history": {"searches": 480, "dates": [{"date": "2014-03-29", "times": 1}, {"date": "2014-03-30", "times": 1}, {"date": "2014-03-31", "times": 9}], "countries": [{"country": "United Kingdom", "times": 1}, {"country": "United States", "times": 10}], "downloads": 361, "records_period": 835908, "s_records": 3984, "downloads_period": 81, "countries_list": ["United Kingdom", "United States"], "records": 5140, "queries": [{"query": "specificepithet:scrofa genus:sus", "times": 6, "records": 38}, {"query": "specificepithet:scrofa genus:Sus", "times": 1, "records": 38}, {"query": "sus scrofa", "times": 2, "records": 38}, {"query": "specificepithet:scrofa genus:sus institutioncode:utep OR CRCM OR hsu OR lacm OR ms OR mvz OR uam OR ummz OR nysm OR psm OR amnh OR cas OR uczm OR ucmp OR fmnh OR ku OR sbmnh OR cuml OR lsumz OR ubcbbm OR mcz OR rom OR tcwc OR nmnh OR dmns OR ccber OR isu OR flmnh", "times": 1, "records": 38}, {"query": "sus scrofa institutioncode:utep OR CRCM OR hsu OR lacm OR msb OR mvz OR uam OR ummz OR nysm OR psm OR amnh OR cas OR uczm OR ucmp OR fmnh OR ku OR sbmnh OR cuml OR lsumz OR ubcbbm OR mcz OR rom OR tcwc OR nmnh OR dmns OR ccber OR isu OR flmnh", "times": 1, "records": 38}]}}