{"github_org": "ypm-vertnet", "last_report_url": "https://api.github.com/repos/jotegui/statReports/contents/data/YPM-ipt_vp_2015_03.json", "downloads": {"downloads_period": 976, "records_unique": 830, "countries_list": ["Chile", "Germany", "Mexico", "Panama", "United States"], "records": 875, "queries": [{"query": "Octodontidae", "records": 512, "times": 1}, {"query": "Capromyidae", "records": 3, "times": 1}, {"query": "stateprovince:\"Baja California\" country:\"Mexico\"", "records": 3, "times": 1}, {"query": "discoglossus", "records": 3, "times": 1}, {"query": "python molurus", "records": 3, "times": 1}, {"query": "tomistoma", "records": 512, "times": 1}, {"query": "elapidae", "records": 3, "times": 3}, {"query": "agamidae", "records": 1, "times": 2}, {"query": "country:\"Mexico\"", "records": 1, "times": 1}, {"query": "stateprovince:\"New Mexico\" class:mammalia", "records": 3, "times": 1}, {"query": "year >= 1800 year <= 2015 distance(location,geopoint(35.9602229692967,-119.37744140625))<100000", "records": 3, "times": 1}, {"query": "Canis latrans", "records": 512, "times": 2}, {"query": "Ochotona", "records": 3, "times": 1}, {"query": "arizona elegans", "records": 1, "times": 1}, {"query": "peromyscus polionotus", "records": 1, "times": 1}, {"query": "Echimyidae", "records": 3, "times": 1}, {"query": "genus:crotalus class:reptilia", "records": 3, "times": 1}, {"query": "gavialis", "records": 1, "times": 1}, {"query": "Caviidae", "records": 512, "times": 1}, {"query": "Canis lupus lupus", "records": 1, "times": 1}, {"query": "Chinchillidae", "records": 3, "times": 1}, {"query": "thamnophis sirtalis", "records": 1, "times": 1}, {"query": "(alytes OR discoglossus)", "records": 3, "times": 1}], "downloads": 27, "countries": [{"country": "Chile", "times": 5}, {"country": "Germany", "times": 2}, {"country": "Mexico", "times": 3}, {"country": "Panama", "times": 2}, {"country": "United States", "times": 15}], "records_period": 7910366, "dates": [{"date": "2015-05-09", "times": 5}, {"date": "2015-05-11", "times": 2}, {"date": "2015-05-12", "times": 1}, {"date": "2015-05-15", "times": 1}, {"date": "2015-05-18", "times": 1}, {"date": "2015-05-19", "times": 2}, {"date": "2015-05-20", "times": 1}, {"date": "2015-05-21", "times": 5}, {"date": "2015-05-22", "times": 2}, {"date": "2015-05-25", "times": 1}, {"date": "2015-05-27", "times": 1}, {"date": "2015-05-29", "times": 5}]}, "github_repo": "ipt-vp", "inst": "YPM", "year": {"searches": 156, "dates": [{"date": "2015-01-03", "times": 1}, {"date": "2015-01-04", "times": 7}, {"date": "2015-01-05", "times": 1}, {"date": "2015-01-08", "times": 3}, {"date": "2015-01-12", "times": 4}, {"date": "2015-01-15", "times": 1}, {"date": "2015-01-16", "times": 1}, {"date": "2015-01-18", "times": 2}, {"date": "2015-01-21", "times": 2}, {"date": "2015-01-22", "times": 1}, {"date": "2015-01-24", "times": 1}, {"date": "2015-01-26", "times": 1}, {"date": "2015-01-28", "times": 3}, {"date": "2015-01-30", "times": 5}], "countries": [{"country": "Brazil", "times": 1}, {"country": "Mexico", "times": 6}, {"country": "Portugal", "times": 2}, {"country": "United States", "times": 19}, {"country": "Unknown", "times": 5}], "downloads": 90, "records_period": 2849158, "s_records": 1627, "downloads_period": 445, "records_unique": 5793, "countries_list": ["Brazil", "Mexico", "Portugal", "United States", "Unknown"], "records": 8797, "queries": [{"query": "Salamandra", "times": 1, "records": 7}, {"query": "Snake Creek class:Mammalia year >= 1929 year <= 1969", "times": 1, "records": 251}, {"query": "canis lupus", "times": 1, "records": 2312}, {"query": "Pilosa", "times": 1, "records": 1}, {"query": "stateprovince:\"Minnesota\" class:Mammalia institutioncode:YPM", "times": 1, "records": 251}, {"query": "stateprovince:\"Minnesota\" class:Mammalia", "times": 2, "records": 7}, {"query": "Procyon lotor", "times": 1, "records": 1}, {"query": "country:\"Mexico\" class:Mammalia year <= 2014", "times": 1, "records": 251}, {"query": "canidae skull", "times": 1, "records": 7}, {"query": "type:specimen stateprovince:\"Virginia\" class:Aves", "times": 1, "records": 1}, {"query": "myotis myotis", "times": 1, "records": 7}, {"query": "Pitheciidae", "times": 1, "records": 1}, {"query": "Scalopus aquaticus", "times": 1, "records": 7}, {"query": "Micrurus fulvius", "times": 1, "records": 251}, {"query": "\"stylemys nebrascensis\" type:specimen fossil:1", "times": 1, "records": 7}, {"query": "Sylvilagus floridanus", "times": 1, "records": 251}, {"query": "county:\"Rosebud\" stateprovince:\"Montana\"", "times": 1, "records": 2}, {"query": "odocoileus virginianus", "times": 1, "records": 7}, {"query": "type:specimen stateprovince:\"Virginia\" class:aves", "times": 1, "records": 7}, {"query": "Dermoptera", "times": 1, "records": 7}, {"query": "Sciurus", "times": 1, "records": 251}, {"query": "stateprovince:\"Kentucky\" class:mammalia", "times": 1, "records": 251}, {"query": "type:specimen stateprovince:\"virginia\" class:aves", "times": 1, "records": 1}, {"query": "gopherus type:specimen fossil:1", "times": 1, "records": 251}, {"query": "Ctenomys", "times": 1, "records": 1}, {"query": "canis latrans", "times": 1, "records": 1}, {"query": "Carnivora america", "times": 1, "records": 1}, {"query": "Discoglossus", "times": 1, "records": 251}, {"query": "Atelidae", "times": 1, "records": 1}, {"query": "type:specimen class:mammalia hastypestatus:1", "times": 1, "records": 7}, {"query": "dermoptera", "times": 1, "records": 7}, {"query": "mummery", "times": 1, "records": 1}]}, "report_month_string": "May, 2015", "searches": {"searches": 76, "dates": [{"date": "2015-05-09", "times": 2}, {"date": "2015-05-11", "times": 1}, {"date": "2015-05-12", "times": 7}, {"date": "2015-05-15", "times": 6}, {"date": "2015-05-17", "times": 1}, {"date": "2015-05-18", "times": 3}, {"date": "2015-05-20", "times": 10}, {"date": "2015-05-21", "times": 4}, {"date": "2015-05-22", "times": 2}, {"date": "2015-05-25", "times": 1}, {"date": "2015-05-26", "times": 14}, {"date": "2015-05-27", "times": 5}, {"date": "2015-05-28", "times": 3}, {"date": "2015-05-29", "times": 8}, {"date": "2015-05-30", "times": 9}], "countries": [{"country": "Belgium", "times": 6}, {"country": "Brazil", "times": 3}, {"country": "Canada", "times": 4}, {"country": "Chile", "times": 1}, {"country": "Germany", "times": 2}, {"country": "India", "times": 6}, {"country": "Mexico", "times": 1}, {"country": "United Kingdom", "times": 1}, {"country": "United States", "times": 52}], "records": 776, "countries_list": ["Belgium", "Brazil", "Canada", "Chile", "Germany", "India", "Mexico", "United Kingdom", "United States"], "queries": [{"query": "thamnophis sirtalis dakota", "records": 1, "times": 1}, {"query": "Giant Panda", "records": 2, "times": 1}, {"query": "genus:Machairodus", "records": 1, "times": 1}, {"query": "Reptil", "records": 1, "times": 1}, {"query": "genus:Smilodon (neonate OR juvenile OR subadult OR sub-adult)", "records": 4, "times": 1}, {"query": "stateprovince:\"Norte de Santander\" country:\"Colombia\" class:Reptilia", "records": 2, "times": 2}, {"query": "Andrewsarchus", "records": 1, "times": 2}, {"query": "Megaladapis", "records": 1, "times": 1}, {"query": "Ailuropoda melanoleuca", "records": 2, "times": 6}, {"query": "python molurus", "records": 1, "times": 1}, {"query": "stateprovince:\"Santander\" country:\"Colombia\" class:Reptilia", "records": 2, "times": 2}, {"query": "genus:megantereon (neonate OR juvenile OR subadult OR sub-adult)", "records": 1, "times": 1}, {"query": "axis", "records": 2, "times": 3}, {"query": "(caudal)", "records": 1, "times": 1}, {"query": "palaeolama", "records": 1, "times": 2}, {"query": "Pachycephalosaurus", "records": 1, "times": 1}, {"query": "glyptodont fossil:1", "records": 1, "times": 1}, {"query": "didelphis fossil:1", "records": 2, "times": 3}, {"query": "browni arizona", "records": 4, "times": 1}, {"query": "Enhydrocyon", "records": 2, "times": 3}, {"query": "Crenidens", "records": 3, "times": 1}, {"query": "afarensis", "records": 2, "times": 1}, {"query": "meiolania", "records": 3, "times": 1}, {"query": "glyptodont", "records": 1, "times": 1}, {"query": "Palaeolama axis fossil:1", "records": 1, "times": 2}, {"query": "Mesonyx", "records": 20, "times": 1}, {"query": "stateprovince:\"New York\" fossil:1", "records": 32, "times": 1}, {"query": "Palaeolama fossil:1", "records": 1, "times": 7}, {"query": "crocuta", "records": 1, "times": 1}, {"query": "genus:smilodon (juvenile OR cub OR subadult OR sub-adult OR neonate)", "records": 4, "times": 1}, {"query": "orycteropus", "records": 2, "times": 2}, {"query": "genus:Dinictis (neonate OR juvenile OR subadult OR sub-adult)", "records": 2, "times": 1}, {"query": "tuberculata institutioncode:YPM", "records": 6, "times": 1}, {"query": "coluber constrictor arizona", "records": 2, "times": 2}, {"query": "genus:Dinictis (cub OR neonate OR juvenile OR subadult OR sub-adult)", "records": 2, "times": 1}, {"query": "tecta institutioncode:YPM", "records": 1, "times": 1}, {"query": "tuberculatus institutioncode:YPM", "records": 4, "times": 1}, {"query": "Entelodontidae", "records": 69, "times": 1}, {"query": "genus:hyaena (cub OR neonate OR juvenile OR subadult OR sub-adult)", "records": 1, "times": 1}, {"query": "discoglossus france", "records": 1, "times": 1}, {"query": "genus:Hoplophoneus (cub OR neonate OR juvenile OR subadult OR sub-adult)", "records": 2, "times": 1}, {"query": "type:specimen country:\"India\" AND (Not Mammalia) fossil:1", "records": 2, "times": 1}, {"query": "type:specimen country:\"India\" fossil:1", "records": 91, "times": 5}, {"query": "class:Mammalia year >= 1850 year <= 1900 distance(location,geopoint(43.58039085560786,-101.337890625))<100000", "records": 100, "times": 1}, {"query": "genus:hoplophoneus (neonate OR juvenile OR subadult OR sub-adult)", "records": 2, "times": 1}, {"query": "Dracorex", "records": 1, "times": 2}, {"query": "Caudiverbera caudiverbera", "records": 1, "times": 1}]}, "report_month": "2015/05", "url": "http://ipt.peabody.yale.edu/ipt/resource.do?r=ipt_vp", "created_at": "2015/06/02", "col": "ipt_vp", "history": {"searches": 216, "records": 43401, "downloads": 105, "records_period": 0, "s_records": 2279, "downloads_period": 0}}